cuffnote/__init__.py
cuffnote/mortgages.py
cuffnote-0.3.12.dist-info/licenses/LICENSE
cuffnote-0.3.12.dist-info/METADATA
cuffnote-0.3.12.dist-info/WHEEL
cuffnote-0.3.12.dist-info/top_level.txt
cuffnote-0.3.12.dist-info/RECORD
