Metadata-Version: 2.4
Name: cuffnote
Version: 0.3.12
Summary: Modeling mortgage loan scenarios
Home-page: https://github.com/bdowdell/cuffnote
Author: Ben Dowdell
Author-email: ben.dowdell87@gmail.com
License: MIT
License-File: LICENSE
Requires-Dist: numpy
Requires-Dist: numpy-financial
Requires-Dist: pandas
Requires-Dist: matplotlib
Dynamic: author
Dynamic: author-email
Dynamic: description
Dynamic: description-content-type
Dynamic: home-page
Dynamic: license
Dynamic: license-file
Dynamic: requires-dist
Dynamic: summary
